{
  "generated_at": "2026-02-06T02:45:19.237282+08:00",
  "total_titles_processed": 448,
  "failed_sources": [],
  "trends": [
    {
      "keyword_group": "书记 部长 秘书 市长 县长 区长 镇长 乡长 局长 处长 科长 主任 村支书 村长 校长 院长 检察长 公职 领导 干部 官员 党员 政府 机关 部门 基层 党委 党组 委员会 市委 县委 区委 管委 村委 官方 人大 政协 政务 党政 执法 调查 监督 大厅 党务 政绩 公务 公车 公款 减负 红头文件 腐败 贪污 受贿 出轨 网爆 举报 调查 被查 通报 问责 形式主义 官僚主义 面子工程",
      "match_count": 20,
      "titles": [
        {
          "title": "宁波通报小洛熙事件调查结果：一级甲等医疗事故，吊销主刀医师执业证书",
          "url": "https://m.thepaper.cn/newsDetail_forward_32540700",
          "source": "澎湃新闻",
          "ranks": [
            1
          ],
          "is_new": false,
          "appearance_count": 3,
          "time_info": "[00时45分 ~ 02时45分]"
        },
        {
          "title": "女婴术后离世,官方通报结果",
          "url": "https://tieba.baidu.com/hottopic/browse/hottopic?topic_id=28350278&amp;topic_name=%E5%A5%B3%E5%A9%B4%E6%9C%AF%E5%90%8E%E7%A6%BB%E4%B8%96%2C%E5%AE%98%E6%96%B9%E9%80%9A%E6%8A%A5%E7%BB%93%E6%9E%9C",
          "source": "贴吧",
          "ranks": [
            1
          ],
          "is_new": false,
          "appearance_count": 3,
          "time_info": "[00时45分 ~ 02时45分]"
        },
        {
          "title": "伊朗最高领袖政治顾问沙姆哈尼获任国防委员会秘书",
          "url": "https://flash.jin10.com/detail/20260206022942871800",
          "source": "金十数据",
          "ranks": [
            1
          ],
          "is_new": true,
          "appearance_count": 1,
          "time_info": "02时45分"
        },
        {
          "title": "伊朗最高领袖政治顾问沙姆哈尼获任国防委员会秘书",
          "url": "https://wallstreetcn.com/livenews/3050838",
          "source": "华尔街见闻-快讯",
          "ranks": [
            4
          ],
          "is_new": true,
          "appearance_count": 1,
          "time_info": "02时45分"
        },
        {
          "title": "欧洲军工股多数收跌，德国莱茵金属RHM跌6.46%，从蒂森克虏伯拆分出来的海事部门跌3.63%，凯傲集团则涨3.10%。 德国上市的WisdomTree Europe Defence UCITS ETF（EUDF.GY）收跌1.72%。 英国伦敦上市、对军工股“照收不误”的Future of Defence UCITS ETF（NATO.LN）收跌1.49%。",
          "url": "https://wallstreetcn.com/livenews/3050820",
          "source": "华尔街见闻-快讯",
          "ranks": [
            2,
            18
          ],
          "is_new": false,
          "appearance_count": 2,
          "time_info": "[01时46分 ~ 02时45分]"
        },
        {
          "title": "英超裁判如何执法赛场冲突",
          "url": "https://search.bilibili.com/all?keyword=%E8%8B%B1%E8%B6%85%E8%A3%81%E5%88%A4%E5%A6%82%E4%BD%95%E6%89%A7%E6%B3%95%E8%B5%9B%E5%9C%BA%E5%86%B2%E7%AA%81",
          "source": "bilibili 热搜",
          "ranks": [
            9,
            7,
            10
          ],
          "is_new": false,
          "appearance_count": 3,
          "time_info": "[00时45分 ~ 02时45分]"
        },
        {
          "title": "官方通报「周生生足金挂坠含铁银钯」，称涉事挂坠送检结果为足金，双方对检测结果无异议，怎样看待这一结果？",
          "url": "https://www.zhihu.com/question/2002855610803249880",
          "source": "知乎",
          "ranks": [
            20,
            9,
            8
          ],
          "is_new": false,
          "appearance_count": 3,
          "time_info": "[00时45分 ~ 02时45分]"
        },
        {
          "title": "国家卫健委工作组赴湖北督促调查精神病医院有关问题",
          "url": "https://m.thepaper.cn/newsDetail_forward_32542825",
          "source": "澎湃新闻",
          "ranks": [
            13,
            12,
            8
          ],
          "is_new": false,
          "appearance_count": 3,
          "time_info": "[00时45分 ~ 02时45分]"
        },
        {
          "title": "海南省人大常委会原党组成员、副主任肖杰接受审查调查",
          "url": "https://m.thepaper.cn/newsDetail_forward_32540901",
          "source": "澎湃新闻",
          "ranks": [
            9,
            10
          ],
          "is_new": false,
          "appearance_count": 3,
          "time_info": "[00时45分 ~ 02时45分]"
        },
        {
          "title": "官方回应男子从着火电车连救3人",
          "url": "https://www.douyin.com/hot/2390977",
          "source": "抖音",
          "ranks": [
            10,
            11
          ],
          "is_new": false,
          "appearance_count": 3,
          "time_info": "[00时45分 ~ 02时45分]"
        },
        {
          "title": "克林顿夫妇就爱泼斯坦调查作证时间确认，将被全程录像，之前二人一直拒绝亲自出席作证，为何突然转变态度？",
          "url": "https://www.zhihu.com/question/2002317830301967379",
          "source": "知乎",
          "ranks": [
            12
          ],
          "is_new": false,
          "appearance_count": 3,
          "time_info": "[00时45分 ~ 02时45分]"
        },
        {
          "title": "受贿5448万余元 杨慧被判14年3个月",
          "url": "https://www.baidu.com/s?wd=%E5%8F%97%E8%B4%BF5448%E4%B8%87%E4%BD%99%E5%85%83+%E6%9D%A8%E6%85%A7%E8%A2%AB%E5%88%A414%E5%B9%B43%E4%B8%AA%E6%9C%88",
          "source": "百度热搜",
          "ranks": [
            17,
            18
          ],
          "is_new": false,
          "appearance_count": 3,
          "time_info": "[00时45分 ~ 02时45分]"
        },
        {
          "title": "郑泽晖任深圳市副市长",
          "url": "https://www.douyin.com/hot/2390766",
          "source": "抖音",
          "ranks": [
            21,
            19,
            20
          ],
          "is_new": false,
          "appearance_count": 3,
          "time_info": "[00时45分 ~ 02时45分]"
        },
        {
          "title": "警方通报女子在洗浴店休息时被猥亵",
          "url": "https://www.toutiao.com/trending/7603341851994800170/",
          "source": "今日头条",
          "ranks": [
            11
          ],
          "is_new": false,
          "appearance_count": 2,
          "time_info": "[01时46分 ~ 02时45分]"
        },
        {
          "title": "在政府发表有关美元购买的言论后，哥伦比亚比索收跌1.63%，至1美元兑3710比索。",
          "url": "https://flash.jin10.com/detail/20260206020707614800",
          "source": "金十数据",
          "ranks": [
            22
          ],
          "is_new": true,
          "appearance_count": 1,
          "time_info": "02时45分"
        },
        {
          "title": "巴西政府：巴西1月份大豆出口量为188万吨，而去年同期为107万吨。",
          "url": "https://flash.jin10.com/detail/20260206020536041800",
          "source": "金十数据",
          "ranks": [
            24
          ],
          "is_new": true,
          "appearance_count": 1,
          "time_info": "02时45分"
        },
        {
          "title": "巴西政府：巴西1月份铁矿石出口量为2854万吨，而去年同期为3089万吨。",
          "url": "https://flash.jin10.com/detail/20260206020522737800",
          "source": "金十数据",
          "ranks": [
            25
          ],
          "is_new": true,
          "appearance_count": 1,
          "time_info": "02时45分"
        },
        {
          "title": "巴西政府：巴西1月糖出口量为202万吨，而去年同期为206万吨。",
          "url": "https://flash.jin10.com/detail/20260206020507344800",
          "source": "金十数据",
          "ranks": [
            26
          ],
          "is_new": true,
          "appearance_count": 1,
          "time_info": "02时45分"
        },
        {
          "title": "沙特阿美将将3月运往亚洲的阿拉伯轻质原油官方售价下调30美分/桶。",
          "url": "https://flash.jin10.com/detail/20260206012331100800",
          "source": "金十数据",
          "ranks": [
            27
          ],
          "is_new": false,
          "appearance_count": 1,
          "time_info": "01时46分"
        },
        {
          "title": "巴西政府：巴西1月份原油出口量为1057万吨，去年同期为933万吨。",
          "url": "https://flash.jin10.com/detail/20260206020446950800",
          "source": "金十数据",
          "ranks": [
            27
          ],
          "is_new": true,
          "appearance_count": 1,
          "time_info": "02时45分"
        }
      ]
    },
    {
      "keyword_group": "山东 济宁",
      "match_count": 2,
      "titles": [
        {
          "title": "宝宝到山东探亲一个月身高猛涨4cm",
          "url": "https://www.toutiao.com/trending/7603219105579368474/",
          "source": "今日头条",
          "ranks": [
            10,
            26
          ],
          "is_new": false,
          "appearance_count": 2,
          "time_info": "[00时45分 ~ 01时46分]"
        },
        {
          "title": "2岁宝宝山东探亲1个月长高4厘米",
          "url": "https://s.weibo.com/weibo?q=%232%E5%B2%81%E5%AE%9D%E5%AE%9D%E5%B1%B1%E4%B8%9C%E6%8E%A2%E4%BA%B21%E4%B8%AA%E6%9C%88%E9%95%BF%E9%AB%984%E5%8E%98%E7%B1%B3%23&t=31&band_rank=30&Refer=top",
          "source": "微博",
          "ranks": [
            30
          ],
          "is_new": false,
          "appearance_count": 1,
          "time_info": "00时45分"
        }
      ]
    }
  ],
  "report_image_url": "https://joyce677.github.io/TrendRadar/img/news.jpg"
}