{
  "generated_at": "2026-01-12T01:16:59.771689+08:00",
  "total_titles_processed": 338,
  "failed_sources": [],
  "trends": [
    {
      "keyword_group": "书记 部长 秘书 市长 县长 区长 镇长 乡长 局长 处长 科长 主任 村支书 村长 校长 院长 检察长 公职 领导 干部 官员 党员 政府 机关 部门 基层 党委 党组 委员会 市委 县委 区委 管委 村委 官方 人大 政协 政务 党政 执法 调查 监督 大厅 党务 政绩 公务 公车 公款 减负 红头文件 腐败 贪污 受贿 出轨 网爆 举报 调查 被查 通报 问责 形式主义 官僚主义 面子工程",
      "match_count": 13,
      "titles": [
        {
          "title": "以色列官员：应做好准备应对伊朗局势，但不应进行干预",
          "url": "https://news.ifeng.com/c/8ppRgtAuFbr",
          "source": "凤凰网",
          "ranks": [
            3
          ],
          "is_new": false,
          "appearance_count": 2,
          "time_info": "[00时23分 ~ 01时16分]"
        },
        {
          "title": "10名干部违规吃喝致1死 9人被处理",
          "url": "https://www.toutiao.com/trending/7594079383007084580/",
          "source": "今日头条",
          "ranks": [
            4
          ],
          "is_new": false,
          "appearance_count": 2,
          "time_info": "[00时23分 ~ 01时16分]"
        },
        {
          "title": "3大牛股明日复牌，16倍牛股天普股份被证监会立案调查",
          "url": "https://www.cls.cn/detail/2254058",
          "source": "财联社热门",
          "ranks": [
            4
          ],
          "is_new": false,
          "appearance_count": 2,
          "time_info": "[00时23分 ~ 01时16分]"
        },
        {
          "title": "拆违引发“冒名执法”争议：湖北黄石一区城管局被判违法后称系街道所为",
          "url": "https://m.thepaper.cn/newsDetail_forward_32326808",
          "source": "澎湃新闻",
          "ranks": [
            5
          ],
          "is_new": false,
          "appearance_count": 2,
          "time_info": "[00时23分 ~ 01时16分]"
        },
        {
          "title": "韩总统府：无意挑衅或刺激朝鲜，将启动军警联合调查",
          "url": "https://news.ifeng.com/c/8ppBa3tBe61",
          "source": "凤凰网",
          "ranks": [
            8
          ],
          "is_new": false,
          "appearance_count": 2,
          "time_info": "[00时23分 ~ 01时16分]"
        },
        {
          "title": "河南10名干部违规吃喝1人死亡",
          "url": "https://s.weibo.com/weibo?q=%23%E6%B2%B3%E5%8D%9710%E5%90%8D%E5%B9%B2%E9%83%A8%E8%BF%9D%E8%A7%84%E5%90%83%E5%96%9D1%E4%BA%BA%E6%AD%BB%E4%BA%A1%23&t=31&band_rank=8&Refer=top",
          "source": "微博",
          "ranks": [
            8,
            15
          ],
          "is_new": false,
          "appearance_count": 2,
          "time_info": "[00时23分 ~ 01时16分]"
        },
        {
          "title": "主播出轨榜一,男友怒撕渣女",
          "url": "https://tieba.baidu.com/hottopic/browse/hottopic?topic_id=28348957&amp;topic_name=%E4%B8%BB%E6%92%AD%E5%87%BA%E8%BD%A8%E6%A6%9C%E4%B8%80%2C%E7%94%B7%E5%8F%8B%E6%80%92%E6%92%95%E6%B8%A3%E5%A5%B3",
          "source": "贴吧",
          "ranks": [
            10
          ],
          "is_new": false,
          "appearance_count": 2,
          "time_info": "[00时23分 ~ 01时16分]"
        },
        {
          "title": "伊朗总统：政府认可和平抗议行为，愿与抗议团体会面",
          "url": "https://wallstreetcn.com/livenews/3034741",
          "source": "华尔街见闻-快讯",
          "ranks": [
            11
          ],
          "is_new": false,
          "appearance_count": 2,
          "time_info": "[00时23分 ~ 01时16分]"
        },
        {
          "title": "卫健局将调查疑小澈住院记录曝光",
          "url": "https://s.weibo.com/weibo?q=%23%E5%8D%AB%E5%81%A5%E5%B1%80%E5%B0%86%E8%B0%83%E6%9F%A5%E7%96%91%E5%B0%8F%E6%BE%88%E4%BD%8F%E9%99%A2%E8%AE%B0%E5%BD%95%E6%9B%9D%E5%85%89%23&t=31&band_rank=22&Refer=top",
          "source": "微博",
          "ranks": [
            22,
            21
          ],
          "is_new": false,
          "appearance_count": 2,
          "time_info": "[00时23分 ~ 01时16分]"
        },
        {
          "title": "伊朗总统：政府认可和平抗议行为 愿与抗议团体会面",
          "url": "https://flash.jin10.com/detail/20260111212521502800",
          "source": "金十数据",
          "ranks": [
            22
          ],
          "is_new": false,
          "appearance_count": 2,
          "time_info": "[00时23分 ~ 01时16分]"
        },
        {
          "title": "赵丽颖接通了李秋萍镇长热线",
          "url": "https://www.douyin.com/hot/2364710",
          "source": "抖音",
          "ranks": [
            27
          ],
          "is_new": false,
          "appearance_count": 2,
          "time_info": "[00时23分 ~ 01时16分]"
        },
        {
          "title": "医生受贿3.5万开药 让销售赚近百万",
          "url": "https://www.baidu.com/s?wd=%E5%8C%BB%E7%94%9F%E5%8F%97%E8%B4%BF3.5%E4%B8%87%E5%BC%80%E8%8D%AF+%E8%AE%A9%E9%94%80%E5%94%AE%E8%B5%9A%E8%BF%91%E7%99%BE%E4%B8%87",
          "source": "百度热搜",
          "ranks": [
            24
          ],
          "is_new": true,
          "appearance_count": 1,
          "time_info": "01时16分"
        },
        {
          "title": "医生受贿3.5万元开具近2万支药品",
          "url": "https://www.toutiao.com/trending/7593147470343929902/",
          "source": "今日头条",
          "ranks": [
            29
          ],
          "is_new": true,
          "appearance_count": 1,
          "time_info": "01时16分"
        }
      ]
    },
    {
      "keyword_group": "山东 济宁",
      "match_count": 3,
      "titles": [
        {
          "title": "山东威海深夜下起“倾盆大瓢雪”",
          "url": "https://www.baidu.com/s?wd=%E5%B1%B1%E4%B8%9C%E5%A8%81%E6%B5%B7%E6%B7%B1%E5%A4%9C%E4%B8%8B%E8%B5%B7%E2%80%9C%E5%80%BE%E7%9B%86%E5%A4%A7%E7%93%A2%E9%9B%AA%E2%80%9D",
          "source": "百度热搜",
          "ranks": [
            8,
            22
          ],
          "is_new": false,
          "appearance_count": 2,
          "time_info": "[00时23分 ~ 01时16分]"
        },
        {
          "title": "山东威海下了倾盆大瓢雪",
          "url": "https://s.weibo.com/weibo?q=%23%E5%B1%B1%E4%B8%9C%E5%A8%81%E6%B5%B7%E4%B8%8B%E4%BA%86%E5%80%BE%E7%9B%86%E5%A4%A7%E7%93%A2%E9%9B%AA%23&t=31&band_rank=9&Refer=top",
          "source": "微博",
          "ranks": [
            9,
            19
          ],
          "is_new": false,
          "appearance_count": 2,
          "time_info": "[00时23分 ~ 01时16分]"
        },
        {
          "title": "山东威海下了“倾盆大瓢雪”",
          "url": "https://www.toutiao.com/trending/7593310390337208326/",
          "source": "今日头条",
          "ranks": [
            27
          ],
          "is_new": false,
          "appearance_count": 1,
          "time_info": "00时23分"
        }
      ]
    }
  ],
  "report_image_url": "https://joyce677.github.io/TrendRadar/img/news.jpg"
}