{
  "generated_at": "2026-04-24T19:06:18.796913+08:00",
  "total_titles_processed": 1455,
  "failed_sources": [],
  "trends": [
    {
      "keyword_group": "书记 部长 秘书 市长 县长 区长 镇长 乡长 局长 处长 科长 主任 村支书 村长 校长 院长 检察长 公职 领导 干部 官员 党员 政府 机关 部门 基层 党委 党组 委员会 市委 县委 区委 管委 村委 官方 人大 政协 政务 党政 执法 调查 监督 大厅 党务 政绩 公务 公车 公款 减负 红头文件 腐败 贪污 受贿 出轨 网爆 举报 调查 被查 通报 问责 形式主义 官僚主义 面子工程",
      "match_count": 64,
      "titles": [
        {
          "title": "受贿数额特别巨大，证监会原党委委员王会民被提起公诉",
          "url": "https://m.thepaper.cn/newsDetail_forward_33032535",
          "source": "澎湃新闻",
          "ranks": [
            4
          ],
          "is_new": false,
          "appearance_count": 9,
          "time_info": "[01时19分 ~ 07时44分]"
        },
        {
          "title": "“公务员300万立案，民企3万立案”？这是误导",
          "url": "https://m.thepaper.cn/newsDetail_forward_33034238",
          "source": "澎湃新闻",
          "ranks": [
            7,
            6,
            5,
            2
          ],
          "is_new": false,
          "appearance_count": 10,
          "time_info": "[01时19分 ~ 10时31分]"
        },
        {
          "title": "一季度全国纪检监察机关立案24.5万件，其中立案省部级干部30人",
          "url": "https://m.thepaper.cn/newsDetail_forward_33032321",
          "source": "澎湃新闻",
          "ranks": [
            1
          ],
          "is_new": false,
          "appearance_count": 7,
          "time_info": "[01时19分 ~ 06时42分]"
        },
        {
          "title": "德国政府：霍尔木兹海峡须永久畅通不设限",
          "url": "https://news.ifeng.com/c/8sZN2up2RU4",
          "source": "凤凰网",
          "ranks": [
            4,
            5
          ],
          "is_new": false,
          "appearance_count": 6,
          "time_info": "[03时06分 ~ 10时31分]"
        },
        {
          "title": "岳麓书院官网被指有“错别字及标点错误”引官方回应，目前多处已更正",
          "url": "https://m.thepaper.cn/newsDetail_forward_33035600",
          "source": "澎湃新闻",
          "ranks": [
            20,
            19,
            18,
            10,
            8,
            7
          ],
          "is_new": false,
          "appearance_count": 13,
          "time_info": "[01时19分 ~ 16时02分]"
        },
        {
          "title": "外网爆出崩铁联动初音未来",
          "url": "https://tieba.baidu.com/hottopic/browse/hottopic?topic_id=28353664&amp;topic_name=%E5%A4%96%E7%BD%91%E7%88%86%E5%87%BA%E5%B4%A9%E9%93%81%E8%81%94%E5%8A%A8%E5%88%9D%E9%9F%B3%E6%9C%AA%E6%9D%A5",
          "source": "贴吧",
          "ranks": [
            10,
            12,
            22,
            25,
            27
          ],
          "is_new": false,
          "appearance_count": 15,
          "time_info": "[01时19分 ~ 19时06分]"
        },
        {
          "title": "官方出手!内存条迎来控价",
          "url": "https://tieba.baidu.com/hottopic/browse/hottopic?topic_id=28353606&amp;topic_name=%E5%AE%98%E6%96%B9%E5%87%BA%E6%89%8B%21%E5%86%85%E5%AD%98%E6%9D%A1%E8%BF%8E%E6%9D%A5%E6%8E%A7%E4%BB%B7",
          "source": "贴吧",
          "ranks": [
            19,
            21
          ],
          "is_new": false,
          "appearance_count": 10,
          "time_info": "[01时19分 ~ 10时31分]"
        },
        {
          "title": "曝黄一鸣出轨",
          "url": "https://www.toutiao.com/trending/7631179671958814783/",
          "source": "今日头条",
          "ranks": [
            22,
            21
          ],
          "is_new": false,
          "appearance_count": 13,
          "time_info": "[01时19分 ~ 16时02分]"
        },
        {
          "title": "百万网红称抓蜈蚣致失明？警方通报",
          "url": "https://www.baidu.com/s?wd=%E7%99%BE%E4%B8%87%E7%BD%91%E7%BA%A2%E7%A7%B0%E6%8A%93%E8%9C%88%E8%9A%A3%E8%87%B4%E5%A4%B1%E6%98%8E%EF%BC%9F%E8%AD%A6%E6%96%B9%E9%80%9A%E6%8A%A5",
          "source": "百度热搜",
          "ranks": [
            25,
            18,
            14,
            22,
            23,
            17
          ],
          "is_new": false,
          "appearance_count": 9,
          "time_info": "[01时19分 ~ 07时44分]"
        },
        {
          "title": "周杰伦谁稀罕官方MV上线",
          "url": "https://search.bilibili.com/all?keyword=%E5%91%A8%E6%9D%B0%E4%BC%A6%E8%B0%81%E7%A8%80%E7%BD%95%E5%AE%98%E6%96%B9MV%E4%B8%8A%E7%BA%BF",
          "source": "bilibili 热搜",
          "ranks": [
            2,
            8,
            6
          ],
          "is_new": false,
          "appearance_count": 5,
          "time_info": "[13时34分 ~ 19时06分]"
        },
        {
          "title": "NBA官方取消布克技术犯规",
          "url": "https://www.douyin.com/hot/2477164",
          "source": "抖音",
          "ranks": [
            4,
            5,
            16
          ],
          "is_new": false,
          "appearance_count": 4,
          "time_info": "[16时01分 ~ 19时06分]"
        },
        {
          "title": "十四届全国人大常委会第二十二次会议4月27日至30日举行",
          "url": "https://flash.jin10.com/detail/20260424102143693800",
          "source": "金十数据",
          "ranks": [
            1
          ],
          "is_new": false,
          "appearance_count": 1,
          "time_info": "10时31分"
        },
        {
          "title": "中国证监会发布《上市公司董事会秘书监管规则》",
          "url": "https://flash.jin10.com/detail/20260424185205678800",
          "source": "金十数据",
          "ranks": [
            1
          ],
          "is_new": true,
          "appearance_count": 1,
          "time_info": "19时06分"
        },
        {
          "title": "官方回应甘肃镇原县发生山体垮塌",
          "url": "https://www.douyin.com/hot/2476682",
          "source": "抖音",
          "ranks": [
            5,
            10,
            21,
            25
          ],
          "is_new": false,
          "appearance_count": 5,
          "time_info": "[10时31分 ~ 17时53分]"
        },
        {
          "title": "伊朗奥委会秘书长：伊朗队尚未确定参加美加墨世界杯",
          "url": "https://news.ifeng.com/c/8sZ2jwcQNW9",
          "source": "凤凰网",
          "ranks": [
            12
          ],
          "is_new": false,
          "appearance_count": 6,
          "time_info": "[01时19分 ~ 07时44分]"
        },
        {
          "title": "教育部门已介入女生被卖到电诈园案",
          "url": "https://s.weibo.com/weibo?q=%23%E6%95%99%E8%82%B2%E9%83%A8%E9%97%A8%E5%B7%B2%E4%BB%8B%E5%85%A5%E5%A5%B3%E7%94%9F%E8%A2%AB%E5%8D%96%E5%88%B0%E7%94%B5%E8%AF%88%E5%9B%AD%E6%A1%88%23&t=31&band_rank=16&Refer=top",
          "source": "微博",
          "ranks": [
            16,
            19,
            23,
            18
          ],
          "is_new": false,
          "appearance_count": 6,
          "time_info": "[03时05分 ~ 06时42分]"
        },
        {
          "title": "学位证被指无效男子举报自己求核查",
          "url": "https://s.weibo.com/weibo?q=%23%E5%AD%A6%E4%BD%8D%E8%AF%81%E8%A2%AB%E6%8C%87%E6%97%A0%E6%95%88%E7%94%B7%E5%AD%90%E4%B8%BE%E6%8A%A5%E8%87%AA%E5%B7%B1%E6%B1%82%E6%A0%B8%E6%9F%A5%23&t=31&band_rank=30&Refer=top",
          "source": "微博",
          "ranks": [
            30
          ],
          "is_new": false,
          "appearance_count": 6,
          "time_info": "[01时19分 ~ 05时44分]"
        },
        {
          "title": "中国证监会发布《上市公司董事会秘书监管规则》，自2026年5月24日起施行。",
          "url": "https://flash.jin10.com/detail/20260424185026492800",
          "source": "金十数据",
          "ranks": [
            3
          ],
          "is_new": true,
          "appearance_count": 1,
          "time_info": "19时06分"
        },
        {
          "title": "黑芝麻：因公司涉嫌信息披露违法违规，中国证券监督管理委员会决定对公司及时任董事长韦清文立案。",
          "url": "https://wallstreetcn.com/livenews/3094001",
          "source": "华尔街见闻-快讯",
          "ranks": [
            4
          ],
          "is_new": true,
          "appearance_count": 1,
          "time_info": "19时06分"
        },
        {
          "title": "“十四五”期间我国版权部门共查处实体市场侵权盗版案件1.28万件",
          "url": "https://flash.jin10.com/detail/20260424100947710800",
          "source": "金十数据",
          "ranks": [
            5
          ],
          "is_new": false,
          "appearance_count": 1,
          "time_info": "10时31分"
        },
        {
          "title": "索马里官员：将限制与以色列有关船只通过曼德海峡",
          "url": "https://wallstreetcn.com/livenews/3093478",
          "source": "华尔街见闻-快讯",
          "ranks": [
            5
          ],
          "is_new": false,
          "appearance_count": 1,
          "time_info": "03时06分"
        },
        {
          "title": "世界读书日前夕，湖北多地市委书记向全市群众推荐了多本好书",
          "url": "https://m.thepaper.cn/newsDetail_forward_33037706",
          "source": "澎湃新闻",
          "ranks": [
            18,
            19
          ],
          "is_new": false,
          "appearance_count": 5,
          "time_info": "[13时34分 ~ 19时06分]"
        },
        {
          "title": "美司法部监察机构调查《爱泼斯坦档案透明法》执行情况",
          "url": "https://flash.jin10.com/detail/20260424062617911800",
          "source": "金十数据",
          "ranks": [
            3,
            20
          ],
          "is_new": false,
          "appearance_count": 2,
          "time_info": "[06时42分 ~ 07时44分]"
        },
        {
          "title": "高校通报“自己举报自己”最新进展",
          "url": "https://www.baidu.com/s?wd=%E9%AB%98%E6%A0%A1%E9%80%9A%E6%8A%A5%E2%80%9C%E8%87%AA%E5%B7%B1%E4%B8%BE%E6%8A%A5%E8%87%AA%E5%B7%B1%E2%80%9D%E6%9C%80%E6%96%B0%E8%BF%9B%E5%B1%95",
          "source": "百度热搜",
          "ranks": [
            5,
            22
          ],
          "is_new": false,
          "appearance_count": 2,
          "time_info": "[17时53分 ~ 19时06分]"
        },
        {
          "title": "英特尔：公司输入成本上涨，存储芯片价格伤害到公司的利润。 预计PC部门将在2026年出现较低的两位数百分比降幅。 近期客户订单模式非常稳健。",
          "url": "https://wallstreetcn.com/livenews/3093538",
          "source": "华尔街见闻-快讯",
          "ranks": [
            5,
            24
          ],
          "is_new": false,
          "appearance_count": 2,
          "time_info": "[05时44分 ~ 06时42分]"
        },
        {
          "title": "演员陈丽君晋升副主任",
          "url": "https://www.toutiao.com/trending/7632185392069971466/",
          "source": "今日头条",
          "ranks": [
            8,
            14,
            17
          ],
          "is_new": false,
          "appearance_count": 4,
          "time_info": "[16时01分 ~ 19时06分]"
        },
        {
          "title": "官方辟谣招录武大图书馆事件当事人",
          "url": "https://www.douyin.com/hot/2475455",
          "source": "抖音",
          "ranks": [
            12
          ],
          "is_new": false,
          "appearance_count": 4,
          "time_info": "[16时01分 ~ 19时06分]"
        },
        {
          "title": "官方通报退伍老兵如厕遭保安拒绝",
          "url": "https://www.toutiao.com/trending/7631064372659798070/",
          "source": "今日头条",
          "ranks": [
            20,
            27,
            25
          ],
          "is_new": false,
          "appearance_count": 4,
          "time_info": "[01时19分 ~ 05时44分]"
        },
        {
          "title": "男子整日疑妻出轨确诊神经梅毒晚期",
          "url": "https://www.toutiao.com/trending/7631082967553622022/",
          "source": "今日头条",
          "ranks": [
            8,
            6
          ],
          "is_new": false,
          "appearance_count": 3,
          "time_info": "[03时05分 ~ 04时51分]"
        },
        {
          "title": "原村支书驾铲车推土埋村民被刑拘",
          "url": "https://www.toutiao.com/trending/7632185954698068022/",
          "source": "今日头条",
          "ranks": [
            6,
            21
          ],
          "is_new": false,
          "appearance_count": 3,
          "time_info": "[16时01分 ~ 17时53分]"
        },
        {
          "title": "演员陈丽君晋升副主任",
          "url": "https://www.baidu.com/s?wd=%E6%BC%94%E5%91%98%E9%99%88%E4%B8%BD%E5%90%9B%E6%99%8B%E5%8D%87%E5%89%AF%E4%B8%BB%E4%BB%BB",
          "source": "百度热搜",
          "ranks": [
            8,
            12
          ],
          "is_new": false,
          "appearance_count": 3,
          "time_info": "[13时34分 ~ 16时02分]"
        },
        {
          "title": "同济博士、上海商学院校长吴忠被实名举报学术不端，论文涉嫌抄袭、一稿多发疑骗经费，具体什么情况？",
          "url": "https://www.zhihu.com/question/2029745974487113974",
          "source": "知乎",
          "ranks": [
            10
          ],
          "is_new": false,
          "appearance_count": 3,
          "time_info": "[01时19分 ~ 04时51分]"
        },
        {
          "title": "原村支书用铲车推土埋村民被刑拘",
          "url": "https://s.weibo.com/weibo?q=%23%E5%8E%9F%E6%9D%91%E6%94%AF%E4%B9%A6%E7%94%A8%E9%93%B2%E8%BD%A6%E6%8E%A8%E5%9C%9F%E5%9F%8B%E6%9D%91%E6%B0%91%E8%A2%AB%E5%88%91%E6%8B%98%23&t=31&band_rank=8&Refer=top",
          "source": "微博",
          "ranks": [
            8
          ],
          "is_new": false,
          "appearance_count": 2,
          "time_info": "[16时01分 ~ 16时02分]"
        },
        {
          "title": "联合国秘书长接班人浮出水面",
          "url": "https://www.toutiao.com/trending/7632101676371869702/",
          "source": "今日头条",
          "ranks": [
            8,
            9
          ],
          "is_new": false,
          "appearance_count": 2,
          "time_info": "[17时53分 ~ 19时06分]"
        },
        {
          "title": "在S-1文件中，SpaceX警告称，政府对Grok AI的调查可能导致公司失去部分市场准入。",
          "url": "https://flash.jin10.com/detail/20260424055631858800",
          "source": "金十数据",
          "ranks": [
            11,
            28
          ],
          "is_new": false,
          "appearance_count": 2,
          "time_info": "[06时42分 ~ 07时44分]"
        },
        {
          "title": "媒体：陈丽君已任浙江小百花越剧院艺术生产与创作部副主任",
          "url": "https://m.thepaper.cn/newsDetail_forward_33041741",
          "source": "澎湃新闻",
          "ranks": [
            15
          ],
          "is_new": false,
          "appearance_count": 2,
          "time_info": "[17时53分 ~ 19时06分]"
        },
        {
          "title": "中国央行等八部门：应用算法推荐技术开展网络营销的 不得设置诱导金融消费者和投资者过度消费的算法模型",
          "url": "https://wallstreetcn.com/livenews/3093926",
          "source": "华尔街见闻-快讯",
          "ranks": [
            7
          ],
          "is_new": false,
          "appearance_count": 1,
          "time_info": "17时53分"
        },
        {
          "title": "欧盟委员会主席冯德莱恩：首批450亿欧元对乌克兰款项可能在二季度就批发。",
          "url": "https://wallstreetcn.com/livenews/3093432",
          "source": "华尔街见闻-快讯",
          "ranks": [
            8
          ],
          "is_new": false,
          "appearance_count": 1,
          "time_info": "01时19分"
        },
        {
          "title": "中国央行等八部门：金融机构及其员工不得委托第三方互联网平台以“投资者教育”“课程培训”等形式变相开展金融产品网络营销",
          "url": "https://wallstreetcn.com/livenews/3093925",
          "source": "华尔街见闻-快讯",
          "ranks": [
            8
          ],
          "is_new": false,
          "appearance_count": 1,
          "time_info": "17时53分"
        },
        {
          "title": "据华尔街日报：耐克将裁员1,400人，约占其员工总数的2%；耐克科技部门裁员人数最多。",
          "url": "https://flash.jin10.com/detail/20260424053005335800",
          "source": "金十数据",
          "ranks": [
            9
          ],
          "is_new": false,
          "appearance_count": 1,
          "time_info": "05时44分"
        },
        {
          "title": "据法院记录及消息人士：印度国有钢铁企业印度钢铁管理局（SAIL）获得法院裁定，暂缓对其钢铁反垄断调查。",
          "url": "https://flash.jin10.com/detail/20260424174817203800",
          "source": "金十数据",
          "ranks": [
            10
          ],
          "is_new": false,
          "appearance_count": 1,
          "time_info": "17时53分"
        },
        {
          "title": "伊朗教育部长：将把本轮美伊战争纳入教材",
          "url": "https://wallstreetcn.com/livenews/3093921",
          "source": "华尔街见闻-快讯",
          "ranks": [
            10
          ],
          "is_new": false,
          "appearance_count": 1,
          "time_info": "17时53分"
        },
        {
          "title": "伊朗领导层集体否认内斗分裂",
          "url": "https://www.toutiao.com/trending/7631334778814398505/",
          "source": "今日头条",
          "ranks": [
            11
          ],
          "is_new": false,
          "appearance_count": 1,
          "time_info": "13时34分"
        },
        {
          "title": "网民造谣江油4.19交通事故被查处",
          "url": "https://www.baidu.com/s?wd=%E7%BD%91%E6%B0%91%E9%80%A0%E8%B0%A3%E6%B1%9F%E6%B2%B94.19%E4%BA%A4%E9%80%9A%E4%BA%8B%E6%95%85%E8%A2%AB%E6%9F%A5%E5%A4%84",
          "source": "百度热搜",
          "ranks": [
            11
          ],
          "is_new": true,
          "appearance_count": 1,
          "time_info": "19时06分"
        },
        {
          "title": "海关总署副署长吴海平会见英国国家打击犯罪总局局长格雷姆·比格",
          "url": "https://flash.jin10.com/detail/20260424154428810800",
          "source": "金十数据",
          "ranks": [
            12
          ],
          "is_new": false,
          "appearance_count": 1,
          "time_info": "16时02分"
        },
        {
          "title": "国防部长董军同俄罗斯国防部长举行会谈",
          "url": "https://wallstreetcn.com/livenews/3093916",
          "source": "华尔街见闻-快讯",
          "ranks": [
            12
          ],
          "is_new": false,
          "appearance_count": 1,
          "time_info": "17时53分"
        },
        {
          "title": "中国证监会发布《上市公司董事会秘书监管规则》",
          "url": "https://wallstreetcn.com/livenews/3093989",
          "source": "华尔街见闻-快讯",
          "ranks": [
            12
          ],
          "is_new": true,
          "appearance_count": 1,
          "time_info": "19时06分"
        },
        {
          "title": "女大学生赴泰国过泼水节被卖缅甸园区，家属转账二十余万对方拒绝放人，警方已立案调查，哪些信息值得关注？",
          "url": "https://www.zhihu.com/question/2030601541254653411",
          "source": "知乎",
          "ranks": [
            14
          ],
          "is_new": false,
          "appearance_count": 1,
          "time_info": "16时02分"
        },
        {
          "title": "男子称用了 16 年的学位证突然被告知「无效」，自我举报求证真伪，如何评价？可能是哪个环节出了问题？",
          "url": "https://www.zhihu.com/question/2030995949602825370",
          "source": "知乎",
          "ranks": [
            15
          ],
          "is_new": true,
          "appearance_count": 1,
          "time_info": "19时06分"
        },
        {
          "title": "市场消息：挪威政府提议社交媒体使用年龄限制为16岁。",
          "url": "https://flash.jin10.com/detail/20260424130308507800",
          "source": "金十数据",
          "ranks": [
            19
          ],
          "is_new": false,
          "appearance_count": 1,
          "time_info": "13时34分"
        },
        {
          "title": "中国商务部部长王文涛会见空客公司首席执行官傅里",
          "url": "https://wallstreetcn.com/livenews/3093623",
          "source": "华尔街见闻-快讯",
          "ranks": [
            20
          ],
          "is_new": false,
          "appearance_count": 1,
          "time_info": "10时31分"
        },
        {
          "title": "上海卫星互联网频谱技术专业委员会正式成立",
          "url": "https://flash.jin10.com/detail/20260424183715827800",
          "source": "金十数据",
          "ranks": [
            21
          ],
          "is_new": true,
          "appearance_count": 1,
          "time_info": "19时06分"
        },
        {
          "title": "美官员称伊朗本周已在霍尔木兹海峡布设更多水雷",
          "url": "https://wallstreetcn.com/livenews/3093700",
          "source": "华尔街见闻-快讯",
          "ranks": [
            21
          ],
          "is_new": false,
          "appearance_count": 1,
          "time_info": "13时34分"
        },
        {
          "title": "伊朗军队总司令：军队在最高领袖领导下保持“一致行动”",
          "url": "https://flash.jin10.com/detail/20260424183648741800",
          "source": "金十数据",
          "ranks": [
            22
          ],
          "is_new": true,
          "appearance_count": 1,
          "time_info": "19时06分"
        },
        {
          "title": "伊朗领导层集体否认内斗分裂：我们都是伊朗人、革命者",
          "url": "https://wallstreetcn.com/livenews/3093461",
          "source": "华尔街见闻-快讯",
          "ranks": [
            22
          ],
          "is_new": false,
          "appearance_count": 1,
          "time_info": "03时06分"
        },
        {
          "title": "狗头萝莉否认出轨",
          "url": "https://s.weibo.com/weibo?q=%23%E7%8B%97%E5%A4%B4%E8%90%9D%E8%8E%89%E5%90%A6%E8%AE%A4%E5%87%BA%E8%BD%A8%23&t=31&band_rank=23&Refer=top",
          "source": "微博",
          "ranks": [
            23
          ],
          "is_new": false,
          "appearance_count": 1,
          "time_info": "13时34分"
        },
        {
          "title": "张玉卓会见巴西公共服务管理与创新部部长埃斯特·德维克",
          "url": "https://flash.jin10.com/detail/20260424183435545800",
          "source": "金十数据",
          "ranks": [
            25
          ],
          "is_new": true,
          "appearance_count": 1,
          "time_info": "19时06分"
        },
        {
          "title": "伊朗军队总司令：军队在最高领袖领导下保持“一致行动”",
          "url": "https://wallstreetcn.com/livenews/3093971",
          "source": "华尔街见闻-快讯",
          "ranks": [
            25
          ],
          "is_new": true,
          "appearance_count": 1,
          "time_info": "19时06分"
        },
        {
          "title": "中国人民银行等八部门有关负责人就《金融产品网络营销管理办法》答记者问",
          "url": "https://flash.jin10.com/detail/20260424173826599800",
          "source": "金十数据",
          "ranks": [
            26
          ],
          "is_new": false,
          "appearance_count": 1,
          "time_info": "17时53分"
        },
        {
          "title": "陈丽君晋升副主任",
          "url": "https://s.weibo.com/weibo?q=%23%E9%99%88%E4%B8%BD%E5%90%9B%E6%99%8B%E5%8D%87%E5%89%AF%E4%B8%BB%E4%BB%BB%23&t=31&band_rank=26&Refer=top",
          "source": "微博",
          "ranks": [
            26
          ],
          "is_new": false,
          "appearance_count": 1,
          "time_info": "10时31分"
        },
        {
          "title": "伊朗强调各级官员之间保持“牢不可破”的团结",
          "url": "https://wallstreetcn.com/livenews/3093890",
          "source": "华尔街见闻-快讯",
          "ranks": [
            28
          ],
          "is_new": false,
          "appearance_count": 1,
          "time_info": "17时53分"
        },
        {
          "title": "美部长称600美元降到10美元是降价600%",
          "url": "https://s.weibo.com/weibo?q=%23%E7%BE%8E%E9%83%A8%E9%95%BF%E7%A7%B0600%E7%BE%8E%E5%85%83%E9%99%8D%E5%88%B010%E7%BE%8E%E5%85%83%E6%98%AF%E9%99%8D%E4%BB%B7600%25%23&t=31&band_rank=29&Refer=top",
          "source": "微博",
          "ranks": [
            29
          ],
          "is_new": false,
          "appearance_count": 1,
          "time_info": "01时19分"
        },
        {
          "title": "英国央行官员警告：股价未能反映当前的风险水平 有可能出现下跌",
          "url": "https://flash.jin10.com/detail/20260424153013395800",
          "source": "金十数据",
          "ranks": [
            30
          ],
          "is_new": false,
          "appearance_count": 1,
          "time_info": "16时02分"
        },
        {
          "title": "新西兰联储调查显示，伊朗战争和选举可能导致信贷需求下降。",
          "url": "https://wallstreetcn.com/livenews/3093686",
          "source": "华尔街见闻-快讯",
          "ranks": [
            30
          ],
          "is_new": false,
          "appearance_count": 1,
          "time_info": "13时34分"
        }
      ]
    },
    {
      "keyword_group": "山东 济宁",
      "match_count": 4,
      "titles": [
        {
          "title": "辽宁舰编号 16，山东舰编号 17，前面 15 个编号是哪些舰船呢？",
          "url": "https://www.zhihu.com/question/430300881",
          "source": "知乎",
          "ranks": [
            16,
            5,
            3,
            2
          ],
          "is_new": false,
          "appearance_count": 4,
          "time_info": "[05时44分 ~ 10时31分]"
        },
        {
          "title": "山东诞生新首富",
          "url": "https://www.baidu.com/s?wd=%E5%B1%B1%E4%B8%9C%E8%AF%9E%E7%94%9F%E6%96%B0%E9%A6%96%E5%AF%8C",
          "source": "百度热搜",
          "ranks": [
            4,
            6
          ],
          "is_new": false,
          "appearance_count": 2,
          "time_info": "[17时53分 ~ 19时06分]"
        },
        {
          "title": "山东新娘输液昏迷92天后初现意识",
          "url": "https://www.baidu.com/s?wd=%E5%B1%B1%E4%B8%9C%E6%96%B0%E5%A8%98%E8%BE%93%E6%B6%B2%E6%98%8F%E8%BF%B792%E5%A4%A9%E5%90%8E%E5%88%9D%E7%8E%B0%E6%84%8F%E8%AF%86",
          "source": "百度热搜",
          "ranks": [
            24,
            8
          ],
          "is_new": false,
          "appearance_count": 3,
          "time_info": "[13时34分 ~ 16时02分]"
        },
        {
          "title": "山东新娘输液昏迷92天后初现意识",
          "url": "https://www.toutiao.com/trending/7631085910114271258/",
          "source": "今日头条",
          "ranks": [
            20
          ],
          "is_new": true,
          "appearance_count": 1,
          "time_info": "19时06分"
        }
      ]
    }
  ],
  "report_image_url": "https://joyce677.github.io/TrendRadar/img/news.jpg"
}